tbot_messages/__init__.py
tbot_messages/admin.py
tbot_messages/apps.py
tbot_messages/messages.py
tbot_messages/models.py
tbot_messages/utils.py
tbot_messages/_generated/__init__.py
tbot_messages/management/__init__.py
tbot_messages/management/commands/__init__.py
tbot_messages/management/commands/create_messages.py
tbot_messages/migrations/__init__.py
django_tbot_messages-0.2.2.dist-info/LICENSE
django_tbot_messages-0.2.2.dist-info/METADATA
django_tbot_messages-0.2.2.dist-info/WHEEL
django_tbot_messages-0.2.2.dist-info/top_level.txt
django_tbot_messages-0.2.2.dist-info/RECORD
