Metadata-Version: 2.1
Name: django-tbot-messages
Version: 0.2.2
Summary: Module for editable messages in your telegram bot
Home-page: https://gitlab.com/frv3r/django-tbot-messages/
Author: frv3r
Author-email: daniil.marchenko@alpha-bots.com
License: MIT
Platform: UNKNOWN
Classifier: Intended Audience :: Developers
Classifier: License :: OSI Approved :: MIT License
Classifier: Operating System :: OS Independent
Classifier: Programming Language :: Python :: 3 :: Only
Classifier: Programming Language :: Python :: 3.10
Classifier: Programming Language :: Python :: Implementation :: CPython
Classifier: Topic :: Software Development :: Libraries :: Application Frameworks
Classifier: Topic :: Software Development :: Libraries :: Python Modules
Classifier: Framework :: Django :: 4.0
License-File: LICENSE
Requires-Dist: Django (>=4.0.2)
Requires-Dist: loguru (>=0.6.0)
Requires-Dist: pyTelegramBotAPI (>=4.4.0)
Requires-Dist: django-tbot-base (>=1.0.1)
Requires-Dist: bot-storage (>=1.0.1)
